wynncraft_waypoint_utils/__init__.py
wynncraft_waypoint_utils/cli.py
wynncraft_waypoint_utils-0.0.3.dist-info/licenses/LICENSE
wynncraft_waypoint_utils-0.0.3.dist-info/METADATA
wynncraft_waypoint_utils-0.0.3.dist-info/WHEEL
wynncraft_waypoint_utils-0.0.3.dist-info/entry_points.txt
wynncraft_waypoint_utils-0.0.3.dist-info/top_level.txt
wynncraft_waypoint_utils-0.0.3.dist-info/RECORD
