Metadata-Version: 2.4
Name: wynncraft-waypoint-utils
Version: 0.0.3
Summary: Wynncraft Waypoint Utils
Author-email: Christoph Matthias Kohnen <mail@cmkohnen.de>
License-Expression: GPL-3.0-or-later
Project-URL: Repository, https://github.com/cmkohnen/wynncraft-waypoint-utils
Project-URL: Issues, https://github.com/cmkohnen/wynncraft-waypoint-utils/issues
Classifier: Programming Language :: Python :: 3
Classifier: Operating System :: OS Independent
Requires-Python: >=3.8
License-File: LICENSE
Dynamic: license-file
